cli.py
ghenv/__init__.py
ghenv/main.py
ghenv-1.0.6.dist-info/METADATA
ghenv-1.0.6.dist-info/WHEEL
ghenv-1.0.6.dist-info/entry_points.txt
ghenv-1.0.6.dist-info/top_level.txt
ghenv-1.0.6.dist-info/RECORD
