Metadata-Version: 2.1
Name: ghenv
Version: 1.0.6
Summary: A CLI tool to manage GitHub environments.
Classifier: Programming Language :: Python :: 3
Classifier: License :: OSI Approved :: MIT License
Classifier: Operating System :: OS Independent
Requires-Python: >=3.10.0
Requires-Dist: certifi (==2022.12.7)
Requires-Dist: cffi (==1.15.1)
Requires-Dist: charset-normalizer (==3.1.0)
Requires-Dist: Deprecated (==1.2.13)
Requires-Dist: idna (==3.4)
Requires-Dist: pycparser (==2.21)
Requires-Dist: PyGithub (==1.58.0)
Requires-Dist: PyJWT (==2.6.0)
Requires-Dist: PyNaCl (==1.5.0)
Requires-Dist: requests (==2.28.2)
Requires-Dist: urllib3 (==1.26.14)
Requires-Dist: wrapt (==1.15.0)
